enthusiast_model_mistral/__init__.py
enthusiast_model_mistral/embedding.py
enthusiast_model_mistral/language_model.py
enthusiast_model_mistral-1.1.0.dist-info/METADATA
enthusiast_model_mistral-1.1.0.dist-info/WHEEL
enthusiast_model_mistral-1.1.0.dist-info/RECORD
